drfrecur/__init__.py
drfrecur/asgi.py
drfrecur/settings.py
drfrecur/urls.py
drfrecur/wsgi.py
drfrecur-0.0.1.dist-info/LICENSE
drfrecur-0.0.1.dist-info/METADATA
drfrecur-0.0.1.dist-info/WHEEL
drfrecur-0.0.1.dist-info/top_level.txt
drfrecur-0.0.1.dist-info/RECORD
